opentf/agent/__init__.py
opentf/agent/agent.py
opentf_agent_nightly-2.0.0.dev263.dist-info/licenses/LICENSE
opentf_agent_nightly-2.0.0.dev263.dist-info/METADATA
opentf_agent_nightly-2.0.0.dev263.dist-info/WHEEL
opentf_agent_nightly-2.0.0.dev263.dist-info/entry_points.txt
opentf_agent_nightly-2.0.0.dev263.dist-info/top_level.txt
opentf_agent_nightly-2.0.0.dev263.dist-info/RECORD
